setup.cfg
setup.py
vpn_porthole.egg-info/PKG-INFO
vpn_porthole.egg-info/SOURCES.txt
vpn_porthole.egg-info/dependency_links.txt
vpn_porthole.egg-info/entry_points.txt
vpn_porthole.egg-info/requires.txt
vpn_porthole.egg-info/top_level.txt
vpnporthole/__init__.py
vpnporthole/argparsetree.py
vpnporthole/cli.py
vpnporthole/ip.py
vpnporthole/session.py
vpnporthole/settings.py
vpnporthole/resources/example.conf
vpnporthole/resources/exec
vpnporthole/resources/profile.spec
vpnporthole/resources/settings.conf
vpnporthole/resources/settings.spec
vpnporthole/system/__init__.py
vpnporthole/system/base.py
vpnporthole/system/darwin.py
vpnporthole/system/linux.py
vpnporthole/system/path.py