Metadata-Version: 1.1
Name: vpn-porthole
Version: 0.0.7
Summary: Splice VPN access into your default network space
Home-page: https://github.com/sourcesimian/vpn-porthole
Author: Source Simian
Author-email: sourcesimian@users.noreply.github.com
License: MIT
Download-URL: https://github.com/sourcesimian/vpn-porthole/tarball/v0.0.7
Platform: UNKNOWN
Classifier: Development Status :: 3 - Alpha
Classifier: Programming Language :: Python :: 3
